morphcards/__init__.py
morphcards/ai.py
morphcards/cli.py
morphcards/core.py
morphcards/database.py
morphcards/demo.py
morphcards-0.1.2.dist-info/METADATA
morphcards-0.1.2.dist-info/WHEEL
morphcards-0.1.2.dist-info/entry_points.txt
morphcards-0.1.2.dist-info/licenses/LICENSE
morphcards-0.1.2.dist-info/RECORD
