Metadata-Version: 2.4
Name: morphcards
Version: 0.1.2
Summary: Spaced Spatial Repetition software with AI-generated sentence variations for language learning
Project-URL: Homepage, https://github.com/felipepenha/morphcards
Project-URL: Documentation, https://github.com/felipepenha/morphcards#readme
Project-URL: Repository, https://github.com/felipepenha/morphcards.git
Project-URL: Issues, https://github.com/felipepenha/morphcards/issues
Project-URL: Changelog, https://github.com/felipepenha/morphcards/blob/main/CHANGELOG.md
Author-email: Felipe Campos Penha <felipe.penha@alumni.usp.br>
Maintainer-email: Felipe Campos Penha <felipe.penha@alumni.usp.br>
License:                                  Apache License
License-File: LICENSE
Keywords: ai,flashcards,fsrs,language-learning,spaced-repetition
Classifier: Development Status :: 3 - Alpha
Classifier: Intended Audience :: Education
Classifier: License :: OSI Approved :: MIT License
Classifier: Programming Language :: Python :: 3
Classifier: Programming Language :: Python :: 3.8
Classifier: Programming Language :: Python :: 3.9
Classifier: Programming Language :: Python :: 3.10
Classifier: Programming Language :: Python :: 3.11
Classifier: Programming Language :: Python :: 3.12
Classifier: Topic :: Education
Classifier: Topic :: Scientific/Engineering :: Artificial Intelligence
Requires-Python: >=3.8
Requires-Dist: duckdb>=0.9.0
Requires-Dist: fsrs==4.0.0
Requires-Dist: google-generativeai>=0.3.0
Requires-Dist: openai>=1.0.0
Requires-Dist: pydantic>=2.0.0
Requires-Dist: python-dotenv>=1.0.0
Requires-Dist: requests>=2.31.0
Provides-Extra: demo
Requires-Dist: gradio>=4.0.0; extra == 'demo'
Requires-Dist: streamlit>=1.28.0; extra == 'demo'
Requires-Dist: websockets>=10.0; extra == 'demo'
Provides-Extra: dev
Requires-Dist: black>=23.0.0; extra == 'dev'
Requires-Dist: isort>=5.0.0; extra == 'dev'
Requires-Dist: mypy>=1.0.0; extra == 'dev'
Requires-Dist: pip-audit; extra == 'dev'
Requires-Dist: pre-commit>=3.0.0; extra == 'dev'
Requires-Dist: pytest-cov>=4.0.0; extra == 'dev'
Requires-Dist: pytest>=7.0.0; extra == 'dev'
Requires-Dist: setuptools>=78.1.1; extra == 'dev'
